Metadata-Version: 1.1
Name: bottle-fdsend
Version: 0.1.1
Summary: Library for constructing responses from file descriptors
Home-page: https://github.com/Outernet-Project/bottle-fdsend
Author: Outernet Inc
Author-email: branko@outernet.is
License: GPLv3
Keywords: file static http response bottle
Platform: UNKNOWN
Classifier: Development Status :: 4 - Beta
Classifier: License :: OSI Approved :: GNU General Public License v3 or later (GPLv3+)
Classifier: Topic :: Internet :: WWW/HTTP :: WSGI
Classifier: Topic :: Internet :: WWW/HTTP :: Dynamic Content
Classifier: Programming Language :: Python :: 3.4
Classifier: Programming Language :: Python :: 2.7
Classifier: Framework :: Bottle
Classifier: Environment :: Web Environment
